DMCpy/DataFile.py
DMCpy/DataSet.py
DMCpy/FileStructure.py
DMCpy/InteractiveViewer.py
DMCpy/Predict.py
DMCpy/RLUAxes.py
DMCpy/Sample.py
DMCpy/TasUBlibDEG.py
DMCpy/Viewer3D.py
DMCpy/__init__.py
DMCpy/_tools.py
DMCpy/calibrationDict.dat
DMCpy/CommandLineScripts/DMCS.py
DMCpy/CommandLineScripts/DMCpy.py
DMCpy/CommandLineScripts/__init__.py
DMCpy/CommandLineScripts/convert.py
DMCpy/CommandLineScripts/ls.py
dmcpy-1.0.3.dist-info/licenses/LICENSE.txt
dmcpy-1.0.3.dist-info/METADATA
dmcpy-1.0.3.dist-info/WHEEL
dmcpy-1.0.3.dist-info/entry_points.txt
dmcpy-1.0.3.dist-info/top_level.txt
dmcpy-1.0.3.dist-info/RECORD
