Metadata-Version: 2.4
Name: DMCpy
Version: 1.0.3
Summary: Python software packaged designed for reduction of neutron powder and single crystal diffraction data from DMC at PSI.
Author-email: Jakob Lass <jakob.lass@psi.ch>, Moody Samuel Harrison <samuel.moody@psi.ch>, Øystein Slagtern Fjellvåg  <oystein.fjellvag@ife.no>
Maintainer-email: Jakob Lass <jakob.lass@psi.ch>, Moody Samuel Harrison <samuel.moody@psi.ch>
Project-URL: Homepage, https://www.psi.ch/en/sinq/dmc/
Project-URL: Documentation, https://DMCpy.readthedocs.org
Project-URL: Repository, https://github.com/Jakob-Lass/DMCPy.git
Project-URL: Bug Tracker, https://github.com/Jakob-Lass/DMCPy/issues
Classifier: Development Status :: 4 - Beta
Classifier: Intended Audience :: Science/Research
Classifier: Intended Audience :: Education
Classifier: Topic :: Scientific/Engineering :: Physics
Classifier: Topic :: Scientific/Engineering :: Visualization
Classifier: Topic :: Scientific/Engineering :: Information Analysis
Classifier: Programming Language :: Python
Classifier: Programming Language :: Python :: 3
Classifier: Programming Language :: Python :: 3.6
Classifier: Programming Language :: Python :: 3.7
Classifier: Programming Language :: Python :: 3.8
Classifier: Programming Language :: Python :: 3.9
Classifier: Programming Language :: Python :: 3.10
Classifier: Programming Language :: Python :: 3.11
Classifier: Programming Language :: Python :: 3.12
Classifier: Operating System :: OS Independent
Requires-Python: >=3.6
License-File: LICENSE.txt
Requires-Dist: matplotlib>=3
Requires-Dist: numpy>=1.14
Requires-Dist: h5py>=2.5
Requires-Dist: scipy>=1.7
Requires-Dist: datetime
Requires-Dist: pandas
Requires-Dist: future
Requires-Dist: tk
Dynamic: license-file
